mcgt/__init__.py
mcgt/__main__.py
mcgt/constants.py
mcgt/phase.py
mcgt/scalar_perturbations.py
mcgt/backends/ref_phase.py
zz_tools/__init__.py
zz_tools/common_io.py
zz_tools-2.3.7.dist-info/licenses/LICENSE
zz_tools-2.3.7.dist-info/licenses/LICENSE-data
zz_tools-2.3.7.dist-info/METADATA
zz_tools-2.3.7.dist-info/WHEEL
zz_tools-2.3.7.dist-info/top_level.txt
zz_tools-2.3.7.dist-info/RECORD
