Metadata-Version: 2.4
Name: zz-tools
Version: 2.3.7
Summary: MCGT utilities
License-Expression: MIT
Project-URL: Homepage, https://github.com/JeanPhilipLalumiere/MCGT
Project-URL: Repository, https://github.com/JeanPhilipLalumiere/MCGT
Classifier: Programming Language :: Python :: 3
Classifier: Programming Language :: Python :: 3 :: Only
Classifier: Operating System :: OS Independent
Classifier: Programming Language :: Python :: 3.9
Classifier: Programming Language :: Python :: 3.10
Classifier: Programming Language :: Python :: 3.11
Classifier: Programming Language :: Python :: 3.12
Classifier: Programming Language :: Python :: 3.13
Requires-Python: >=3.9
License-File: LICENSE
License-File: LICENSE-data
Requires-Dist: numpy<2.1
Requires-Dist: pandas>=2.0
Dynamic: license-file
